Metadata-Version: 2.1
Name: normalize
Version: 3.0.1
Summary: Declarative Python meta-model system and visitor utilities
Home-page: http://hearsaycorp.github.io/normalize
Author: Hearsay Social
Author-email: opensource@hearsaysocial.com
License: MIT
Classifier: Development Status :: 5 - Production/Stable
Classifier: License :: OSI Approved :: MIT License
Classifier: Programming Language :: Python
Classifier: Programming Language :: Python :: 3
Classifier: Programming Language :: Python :: 3.6
Classifier: Programming Language :: Python :: 3.7
Classifier: Programming Language :: Python :: 3.8
Classifier: Programming Language :: Python :: 3.9
Classifier: Programming Language :: Python :: 3.10
Classifier: Programming Language :: Python :: 3.11
Classifier: Programming Language :: Python :: Implementation :: CPython
Classifier: Topic :: Software Development :: Libraries :: Python Modules
License-File: LICENSE.txt
License-File: AUTHORS.rst
Requires-Dist: richenum >=1.0.0
